hehe_maker-1.3.19.dist-info/DESCRIPTION.rst
hehe_maker-1.3.19.dist-info/METADATA
hehe_maker-1.3.19.dist-info/RECORD
hehe_maker-1.3.19.dist-info/WHEEL
hehe_maker-1.3.19.dist-info/entry_points.txt
hehe_maker-1.3.19.dist-info/metadata.json
hehe_maker-1.3.19.dist-info/top_level.txt
hehemaker/__init__.py
hehemaker/autoarticle.py
hehemaker/hehemaker.py
