Metadata-Version: 2.0
Name: hehe-maker
Version: 1.3.19
Summary: A simple command line tool to modify papers in PDF format. Can also create new articles from PDF(s).
Home-page: https://github.com/ginger51011/hehe-maker
Author: Emil Jonathan Eriksson
Author-email: eje1999@gmail.com
License: UNKNOWN
Platform: UNKNOWN
Requires-Python: >3.0.0
Requires-Dist: pdfrw
Requires-Dist: pdfminer
Requires-Dist: markovify
